natural2lean_cli/__init__.py
natural2lean_cli/__main__.py
natural2lean_cli/file.py
natural2lean_cli/interactive.py
natural2lean_cli/utils/__init__.py
natural2lean_cli/utils/progress_indicator.py
natural2lean_cli/utils/text.py
natural2lean_cli-0.0.2.dist-info/LICENSE
natural2lean_cli-0.0.2.dist-info/METADATA
natural2lean_cli-0.0.2.dist-info/WHEEL
natural2lean_cli-0.0.2.dist-info/entry_points.txt
natural2lean_cli-0.0.2.dist-info/top_level.txt
natural2lean_cli-0.0.2.dist-info/RECORD
