Metadata-Version: 2.1
Name: natural2lean-cli
Version: 0.0.2
Summary: Command line interface for natural2lean package
Home-page: https://github.com/Augustindou/natural2lean-cli
Author: Augustin d'Oultremont
Author-email: Augustin d'Oultremont <augustin.doultremont@outlook.com>
License: MIT License        
Project-URL: Homepage, https://github.com/Augustindou/natural2lean-cli
Keywords: auto-formalization,parser,interactive
Classifier: License :: OSI Approved :: MIT License
Classifier: Programming Language :: Python
Classifier: Programming Language :: Python :: 3
Requires-Python: >=3.9
License-File: LICENSE
Requires-Dist: natural2lean (>=0.0.3)
Requires-Dist: inquirerpy
Provides-Extra: dev
Requires-Dist: pytest (>=3.6) ; extra == 'dev'
Requires-Dist: pyperclip ; extra == 'dev'
Requires-Dist: black ; extra == 'dev'
